qboot/__init__.py
qboot/cli.py
qboot-0.1.1.dist-info/licenses/LICENSE
qboot-0.1.1.dist-info/METADATA
qboot-0.1.1.dist-info/WHEEL
qboot-0.1.1.dist-info/entry_points.txt
qboot-0.1.1.dist-info/top_level.txt
qboot-0.1.1.dist-info/RECORD
