Metadata-Version: 2.4
Name: qboot
Version: 0.1.1
Summary: A simple yet powerful tool to bootstrap a modern Python project.
Author-email: Youngmin Kim <ggred0123@gmail.com>
License: Copyright (c) 2025 Youngmin Kim
Project-URL: Homepage, https://github.com/ggred0123/qboot
Project-URL: Bug Tracker, https://github.com/ggred0123/qboot/issues
Keywords: boot,init,scaffolding,template,automation,dev-tools
Classifier: Development Status :: 4 - Beta
Classifier: Intended Audience :: Developers
Classifier: Topic :: Software Development :: Build Tools
Classifier: License :: OSI Approved :: MIT License
Classifier: Operating System :: OS Independent
Classifier: Programming Language :: Python :: 3
Classifier: Programming Language :: Python :: 3.9
Classifier: Programming Language :: Python :: 3.10
Classifier: Programming Language :: Python :: 3.11
Classifier: Programming Language :: Python :: 3.12
Requires-Python: >=3.9
License-File: LICENSE
Dynamic: license-file
